<?xml version="1.0" encoding="UTF-8" standalone="yes"?>
<addons>
<addon id="script.program.FTVhulu"
  name="Hulu"
  version="1.0"
  provider-name="elmerohueso">
  <requires>
    <import addon="xbmc.python" version="2.1.0"/>
  </requires>
  <extension point="xbmc.python.script" library="addon.py">
    <provides>video</provides>
  </extension>
  <extension point="xbmc.addon.metadata">
    <platform>android</platform>
    <summary lang="en">Hulu shortcut for Android</summary>
    <description lang="en">Launches the Hulu app on the Android.  Can be added to the Home screen under the video categories for quick access.</description>
	<disclaimer>Must already have the Hulu app installed.</disclaimer>
  </extension>
</addon>

<addon id="script.program.FTVnetflix"
  name="Netflix"
  version="1.2"
  provider-name="elmerohueso">
  <requires>
    <import addon="xbmc.python" version="2.1.0"/>
  </requires>
  <extension point="xbmc.python.script" library="addon.py">
    <provides>video</provides>
  </extension>
  <extension point="xbmc.addon.metadata">
    <platform>android</platform>
    <summary lang="en">Netflix shortcut for the Amazon FireTV</summary>
    <description lang="en">Launches the Netflix app on the Amazon FireTV.  Can be added to the Home screen under the video categories for quick access</description>
	<disclaimer>This only works with the Fire TV's version of Netflix.  It will not work with the general Android version.</disclaimer>
  </extension>
</addon>

<addon id="script.screensaver.logoff" name="Logoff" version="1.0" provider-name="elmerohueso">
  <requires>
    <import addon="xbmc.python" version="2.1.0"/>
  </requires>
  <extension point="xbmc.ui.screensaver" library="addon.py">
	<provides></provides>
  </extension>
  <extension point="xbmc.addon.metadata">
    <platform>all</platform>
    <summary>"Screensaver" that will log off your XBMC profile</summary>
    <description>Not really a screensaver, but makes your system automatically log off an XBMC profile according to your "Screensaver time".</description>
  </extension>
</addon>

<addon
  id="skin.confluenceFTVkiosk"
  version="1.0"
  name="Confluence (Fire TV Kiosk)"
  provider-name="Jezz_X, Team XBMC, modified by elmerohueso">
  <requires>
    <import addon="xbmc.gui" version="5.0.0"/>
  </requires>
  <extension
    point="xbmc.gui.skin"
    defaultthemename="textures.xbt"
    debugging="false"
    effectslowdown="0.75">
    <res width="1280" height="720" aspect="16:9" default="true" folder="720p" />
  </extension>
  <extension point="xbmc.addon.metadata">
    <summary lang="en">Confluence skin by Jezz_X. (XBMC's default skin), modified by elmerohueso.</summary>
    <description lang="en">The default Confluence skin with some modifications, meant to go with elmerohueso's Launcher build of XBMC for the Amazon Fire TV (see http://forum.xda-developers.com/showthread.php?t=2790392).</description>
    <platform>all</platform>
  </extension>
</addon>

<addon id="xbmc.repo.elmerohueso" name="elmerohueso's Add-on Repository" version="1.0" provider-name="elmerohueso">
    <extension point="xbmc.addon.repository" name="elmerohueso's Add-on Repository">
        <info>http://github.com/elmerohueso/xbmc.repo.elmerohueso/raw/master/download/addons.xml</info>
        <checksum>http://github.com/elmerohueso/xbmc.repo.elmerohueso/raw/master/download/addons.xml.md5</checksum>
        <datadir zip="true">https://github.com/elmerohueso/xbmc.repo.elmerohueso/raw/master/download/</datadir>
    </extension>
    <extension point="xbmc.addon.metadata">
        <summary>elmerohueso's Add-on Repository</summary>
        <description>elmerohueso's Add-on Repository</description>
        <platform>all</platform>
    </extension>
</addon>
</addons>
